BioBeee/DrugbankBee.py
BioBeee/__init__.py
BioBeee/ebiBee.py
BioBeee/system.py
BioBeee/tagsHandler.py
BioBeee/BioProcessing/DistanceTools.py
BioBeee/BioProcessing/Statistics.py
BioBeee/BioProcessing/__init__.py
BioBeee/BioProcessing/analysis.py
BioBeee/BioProcessing/bioGraph.py
BioBeee/Entrez/__init__.py
BioBeee/Entrez/config.py
BioBeee/Entrez/pydirect.py
BioBeee/Formats/BioParser.py
BioBeee/Formats/IO.py
BioBeee/Formats/__init__.py
BioBeee-0.0.5.dist-info/LICENSE
BioBeee-0.0.5.dist-info/METADATA
BioBeee-0.0.5.dist-info/WHEEL
BioBeee-0.0.5.dist-info/top_level.txt
BioBeee-0.0.5.dist-info/RECORD
