Metadata-Version: 2.1
Name: BioBeee
Version: 0.0.5
Summary: Bioinformatics tool for performing web scrapping on biological database and pre-processing
Home-page: https://gitlab.com/aniket4033426/mini_project
Author: aniket_yadav
Author-email: aniketyadav8687@gmail.com
License: MIT
Requires-Python: >=3.0
License-File: LICENSE
Requires-Dist: beautifulsoup4 >=4.11.1
Requires-Dist: requests >=2.28.1
Requires-Dist: requests-oauthlib >=1.3.1
